avtskills/__init__.py
avtskills/_sales_prompt.py
avtskills/_skill_utils.py
avtskills/skills.py
jamblaki_skillset-0.1.0.dist-info/METADATA
jamblaki_skillset-0.1.0.dist-info/WHEEL
jamblaki_skillset-0.1.0.dist-info/top_level.txt
jamblaki_skillset-0.1.0.dist-info/RECORD
