Metadata-Version: 2.1
Name: jamblaki_skillset
Version: 0.1.0
Summary: A library of skills defined for Jamblaki
Author: Jamblaki
Author-email: jamblaki@test.com
Classifier: Programming Language :: Python :: 3
Classifier: License :: OSI Approved :: MIT License
Classifier: Operating System :: OS Independent
Requires-Python: >=3.10
Requires-Dist: openai
